{
  "plugins": {
    "catppuccin": {
      "rev": "ce4a8e0d5267e67056f9f4dcf6cb1d0933c8ca00",
      "src": "https://github.com/catppuccin/nvim"
    },
    "diffview.nvim": {
      "rev": "4516612",
      "src": "https://github.com/sindrets/diffview.nvim"
    },
    "gitsigns.nvim": {
      "rev": "5813e4878748805f1518cee7abb50fd7205a3a48",
      "src": "https://github.com/lewis6991/gitsigns.nvim"
    },
    "mini.nvim": {
      "rev": "c007f4b3822c99b98328bc214589a721c69d1514",
      "src": "https://github.com/echasnovski/mini.nvim"
    },
    "nvim-lspconfig": {
      "rev": "07f4e93de92e8d4ea7ab99602e3a8c9ac0fb778a",
      "src": "https://github.com/neovim/nvim-lspconfig"
    },
    "nvim-treesitter": {
      "rev": "17885756e63df73ed90db62e4630f744ceda6514",
      "src": "https://github.com/nvim-treesitter/nvim-treesitter",
      "version": "'main'"
    },
    "nvim-treesitter-context": {
      "rev": "660861b1849256398f70450afdf93908d28dc945",
      "src": "https://github.com/nvim-treesitter/nvim-treesitter-context"
    },
    "oil.nvim": {
      "rev": "01cb3a8ad7d5e8707041edc775af83dbf33838f4",
      "src": "https://github.com/stevearc/oil.nvim"
    },
    "snacks.nvim": {
      "rev": "fe7cfe9800a182274d0f868a74b7263b8c0c020b",
      "src": "https://github.com/folke/snacks.nvim"
    },
    "vim-eunuch": {
      "rev": "e86bb79",
      "src": "https://github.com/tpope/vim-eunuch"
    },
    "vim-fugitive": {
      "rev": "61b51c0",
      "src": "https://github.com/tpope/vim-fugitive"
    }
  }
}