{
  "plugins": {
    "catppuccin": {
      "rev": "beaf41a30c26fd7d6c386d383155cbd65dd554cd",
      "src": "https://github.com/catppuccin/nvim"
    },
    "diffview.nvim": {
      "rev": "4516612fe98ff56ae0415a259ff6361a89419b0a",
      "src": "https://github.com/sindrets/diffview.nvim"
    },
    "gitsigns.nvim": {
      "rev": "42d6aed4e94e0f0bbced16bbdcc42f57673bd75e",
      "src": "https://github.com/lewis6991/gitsigns.nvim"
    },
    "mini.nvim": {
      "rev": "c9d3bc2df3015d82eabe3d2d88dac1ef5746e9e8",
      "src": "https://github.com/echasnovski/mini.nvim"
    },
    "nvim-lspconfig": {
      "rev": "92ee7d42320edfbb81f3cad851314ab197fa324a",
      "src": "https://github.com/neovim/nvim-lspconfig"
    },
    "nvim-treesitter": {
      "rev": "8aada0e3940c573e38b417a226b43bc8675f8958",
      "src": "https://github.com/nvim-treesitter/nvim-treesitter",
      "version": "'main'"
    },
    "nvim-treesitter-context": {
      "rev": "64dd4cf3f6fd0ab17622c5ce15c91fc539c3f24a",
      "src": "https://github.com/nvim-treesitter/nvim-treesitter-context"
    },
    "oil.nvim": {
      "rev": "6b59a6cf623fa2245c7454ddb458df5bdb6615d3",
      "src": "https://github.com/stevearc/oil.nvim"
    },
    "snacks.nvim": {
      "rev": "fe7cfe9800a182274d0f868a74b7263b8c0c020b",
      "src": "https://github.com/folke/snacks.nvim"
    },
    "vim-eunuch": {
      "rev": "e86bb79",
      "src": "https://github.com/tpope/vim-eunuch"
    },
    "vim-fugitive": {
      "rev": "61b51c0",
      "src": "https://github.com/tpope/vim-fugitive"
    }
  }
}